connect_mongodb/__init__.py
connect_mongodb-0.0.1.dist-info/LICENSE.txt
connect_mongodb-0.0.1.dist-info/METADATA
connect_mongodb-0.0.1.dist-info/WHEEL
connect_mongodb-0.0.1.dist-info/top_level.txt
connect_mongodb-0.0.1.dist-info/RECORD
