Metadata-Version: 2.1
Name: connect-mongodb
Version: 0.0.1
Summary: Connect mongoDb with python
Home-page: https://github.com/KaranJani/PyPi-connect_mongodb
Author: Karan Jani
License: UNKNOWN
Keywords: mongodb,python,connect mongodb with python,connect to mongodb
Platform: UNKNOWN
Classifier: Programming Language :: Python :: 3
Classifier: License :: OSI Approved :: MIT License
Classifier: Operating System :: OS Independent
Requires-Python: >=3.6
License-File: LICENSE.txt
Requires-Dist: pymongo
Requires-Dist: pymongo[srv]
